Metadata-Version: 2.1
Name: kafkawrapper
Version: 1.0.3
Summary: A wrapper for Kafka producer
Home-page: UNKNOWN
Author: Pradeep
Author-email: pradeep@incaendo.com
License: MIT
Platform: UNKNOWN
